{
  "posts": [
    {
      "id": 1,
      "title": "json-server",
      "author": "typicode"
    }
  ],
  "comments": [
    {
      "id": 1,
      "body": "some comment",
      "postId": 1
    }
  ],
  "profile": {
    "name": "typicode"
  },
  "people": [
    {
      "id": 1,
      "name": "Michał",
      "surname": "Kryński",
      "position": "Frontend developer",
      "address": "Michałowo",
      "phone": 123456789,
      "birthdate": "01/17/2017"
    },
    {
      "id": 2,
      "name": "Piotrek",
      "surname": "Tarasiuk",
      "position": "FullStack developer",
      "address": "Białostoczek",
      "phone": 123456789,
      "birthdate": "04/17/2017"
    },
    {
      "id": 3,
      "name": "Paweł",
      "surname": "Siemieniuk",
      "position": "Frontend developer",
      "address": "Bojary",
      "phone": 123456789,
      "birthdate": "04/17/2017"
    },
    {
      "id": 4,
      "name": "Roman",
      "surname": "Jarmoc",
      "position": "FullStack developer",
      "address": "Nowe Miasto",
      "phone": 123456789,
      "birthdate": "04/17/2017"
    }
  ]
}